spotify_recommender_api/__init__.py
spotify_recommender_api/error.py
spotify_recommender_api/recommender.py
spotify_recommender_api/util.py
spotify_recommender_api/visualization.py
spotify_recommender_api/artist/__init__.py
spotify_recommender_api/artist/artist.py
spotify_recommender_api/auth/__init__.py
spotify_recommender_api/auth/authentication.py
spotify_recommender_api/auth/web_authentication.py
spotify_recommender_api/core/__init__.py
spotify_recommender_api/core/knn_algorithm.py
spotify_recommender_api/core/library.py
spotify_recommender_api/playlist/__init__.py
spotify_recommender_api/playlist/base_playlist.py
spotify_recommender_api/playlist/features.py
spotify_recommender_api/playlist/liked_songs.py
spotify_recommender_api/playlist/playlist.py
spotify_recommender_api/playlist/util.py
spotify_recommender_api/requests/__init__.py
spotify_recommender_api/requests/api_handler.py
spotify_recommender_api/requests/auth_handler.py
spotify_recommender_api/requests/request_handler.py
spotify_recommender_api/server/__init__.py
spotify_recommender_api/server/sensitive.py
spotify_recommender_api/server/server.py
spotify_recommender_api/song/__init__.py
spotify_recommender_api/song/song.py
spotify_recommender_api/song/util.py
spotify_recommender_api/user/__init__.py
spotify_recommender_api/user/user.py
spotify_recommender_api/user/util.py
spotify_recommender_api/web/__init__.py
spotify_recommender_api/web/main.py
spotify_recommender_api-5.4.5.dist-info/METADATA
spotify_recommender_api-5.4.5.dist-info/WHEEL
spotify_recommender_api-5.4.5.dist-info/top_level.txt
spotify_recommender_api-5.4.5.dist-info/RECORD
