Metadata-Version: 2.1
Name: spotify-recommender-api
Version: 5.4.5
Summary: Python package which takes the songs of a greater playlist as starting point to make recommendations of groups of songs that might bond well within that same playlist, using K-Nearest-Neighbors Technique
Home-page: https://github.com/nikolas-virionis/spotify-api
Author: Nikolas B Virionis
Author-email: nikolas.virionis@gmail.com
License: UNKNOWN
Platform: UNKNOWN
Classifier: Programming Language :: Python :: 3
Classifier: Programming Language :: Python :: 3.8
Requires-Python: >=3
Requires-Dist: fastapi
Requires-Dist: matplotlib
Requires-Dist: pandas
Requires-Dist: requests
Requires-Dist: seaborn
Requires-Dist: uvicorn
